sendflowdev/__init__.py
sendflowdev-1.0.0.dist-info/METADATA
sendflowdev-1.0.0.dist-info/WHEEL
sendflowdev-1.0.0.dist-info/top_level.txt
sendflowdev-1.0.0.dist-info/RECORD
